pyDSAlgo/__init__.py
pyDSAlgo/Algo/__init__.py
pyDSAlgo/Algo/Sorting/Py3WayMergeSort.py
pyDSAlgo/Algo/Sorting/PyBIngoSort.py
pyDSAlgo/Algo/Sorting/PyBitonicSort.py
pyDSAlgo/Algo/Sorting/PyBogoSort.py
pyDSAlgo/Algo/Sorting/PyBubbleSort.py
pyDSAlgo/Algo/Sorting/PyBucketSort.py
pyDSAlgo/Algo/Sorting/PyCocktailSort.py
pyDSAlgo/Algo/Sorting/PyCombSort.py
pyDSAlgo/Algo/Sorting/PyCountingSort.py
pyDSAlgo/Algo/Sorting/PyCycleSort.py
pyDSAlgo/Algo/Sorting/PyGnomeSort.py
pyDSAlgo/Algo/Sorting/PyHeapSort.py
pyDSAlgo/Algo/Sorting/PyInsertionSort.py
pyDSAlgo/Algo/Sorting/PyMergeSort.py
pyDSAlgo/Algo/Sorting/PyOddEvenSort.py
pyDSAlgo/Algo/Sorting/PyPancakeSort.py
pyDSAlgo/Algo/Sorting/PyPigeonholeSort.py
pyDSAlgo/Algo/Sorting/PyQuickSort.py
pyDSAlgo/Algo/Sorting/PyRadixSort.py
pyDSAlgo/Algo/Sorting/PySelectionSort.py
pyDSAlgo/Algo/Sorting/PyShellSort.py
pyDSAlgo/Algo/Sorting/PySleepSort.py
pyDSAlgo/Algo/Sorting/PyStoogeSort.py
pyDSAlgo/Algo/Sorting/PyStrandSort.py
pyDSAlgo/Algo/Sorting/PyTagSort.py
pyDSAlgo/Algo/Sorting/PyTimSort.py
pyDSAlgo/Algo/Sorting/PyTreeSort.py
pyDSAlgo/Algo/Sorting/__init__.py
pyDSAlgo/DS/__init__.py
pyDSAlgo/DS/Graph/PyGraph.py
pyDSAlgo/DS/Graph/PyLinkedGraph.py
pyDSAlgo/DS/Graph/__init__.py
pyDSAlgo/DS/Heap/PyMaxHeap.py
pyDSAlgo/DS/Heap/PyMinHeap.py
pyDSAlgo/DS/Heap/__init__.py
pyDSAlgo/DS/LinkedList/PyCircularLinkedList.py
pyDSAlgo/DS/LinkedList/PyDoublyCircularLinkedLIst.py
pyDSAlgo/DS/LinkedList/PyDoublyLinkedList.py
pyDSAlgo/DS/LinkedList/PyHeaderLinkedList.py
pyDSAlgo/DS/LinkedList/PyLinkedList.py
pyDSAlgo/DS/LinkedList/PySkipLinkedList.py
pyDSAlgo/DS/LinkedList/__init__.py
pyDSAlgo/DS/Queue/PyCircularQueue.py
pyDSAlgo/DS/Queue/PyDeque.py
pyDSAlgo/DS/Queue/PyPriorityQueue.py
pyDSAlgo/DS/Queue/PyQueue.py
pyDSAlgo/DS/Queue/__init__.py
pyDSAlgo/DS/Stack/PyStack.py
pyDSAlgo/DS/Stack/__init__.py
pyDSAlgo/DS/Stack/pyLinkedStack.py
pyDSAlgo/DS/Tree/PyAVLTree.py
pyDSAlgo/DS/Tree/PyBTree.py
pyDSAlgo/DS/Tree/PyBinarySearchTree.py
PyDSAlgo-1.1.0.dist-info/LICENSE
PyDSAlgo-1.1.0.dist-info/METADATA
PyDSAlgo-1.1.0.dist-info/WHEEL
PyDSAlgo-1.1.0.dist-info/top_level.txt
PyDSAlgo-1.1.0.dist-info/RECORD
